chino/__init__.py
chino/__main__.py
chino/conversation.py
chino/migrations.py
chino/query.py
chino/utils.py
chinoai-1.0.0.dist-info/LICENSE
chinoai-1.0.0.dist-info/METADATA
chinoai-1.0.0.dist-info/WHEEL
chinoai-1.0.0.dist-info/entry_points.txt
chinoai-1.0.0.dist-info/top_level.txt
chinoai-1.0.0.dist-info/RECORD
