Metadata-Version: 2.1
Name: chinoai
Version: 1.0.0
Summary: Chino is a terminal based chatbot based on ChatGPT.
Author-email: Sam <asamadans@gmail.com>
License: MIT License
Project-URL: Homepage, https://github.com/SAMAD101/Chino
Keywords: chatbot,terminal,openai,rag,bumpver
Classifier: License :: OSI Approved :: MIT License
Classifier: Programming Language :: Python
Classifier: Programming Language :: Python :: 3
Requires-Python: >=3.11
License-File: LICENSE
Requires-Dist: langchain >=0.1.6
Requires-Dist: langchain-community >=0.0.19
Requires-Dist: langchain-openai >=0.0.5
Requires-Dist: typer[all] >=0.9.0
Requires-Dist: unstructured[pdf] >=0.11.8
Requires-Dist: chromadb >=0.4.22
Provides-Extra: dev
Requires-Dist: black ; extra == 'dev'
Requires-Dist: pytest ; extra == 'dev'
Requires-Dist: pre-commit ; extra == 'dev'
Requires-Dist: twine ; extra == 'dev'
Provides-Extra: test
Requires-Dist: pytest ; extra == 'test'
